primevalidation/__init__.py.py
primevalidation/prime.py
primevalidation-0.1.0.dist-info/METADATA
primevalidation-0.1.0.dist-info/WHEEL
primevalidation-0.1.0.dist-info/licenses/LICENSE
primevalidation-0.1.0.dist-info/RECORD
