Metadata-Version: 2.4
Name: primevalidation
Version: 0.1.0
Summary: A simple Python library to validate if a number is prime.
Project-URL: Homepage, https://github.com/yourusername/primevalidation
Project-URL: Repository, https://github.com/yourusername/primevalidation
Project-URL: Issues, https://github.com/yourusername/primevalidation/issues
Author-email: Your Name <your.email@example.com>
License: 
License-File: LICENSE
Keywords: math,number theory,prime,validation
Classifier: License :: OSI Approved :: MIT License
Classifier: Operating System :: OS Independent
Classifier: Programming Language :: Python :: 3
Classifier: Topic :: Scientific/Engineering :: Mathematics
Requires-Python: >=3.8
